<nuds xmlns="http://nomisma.org/nuds" xmlns:xsi="http://www.w3.org/2001/XMLSchema-instance" xmlns:xs="http://www.w3.org/2001/XMLSchema" xmlns:xlink="http://www.w3.org/1999/xlink" recordType="conceptual">
    <control>
        <recordId>ric.4.pn.34B</recordId>
        <otherRecordId semantic="skos:broader">ric.4.pn.34</otherRecordId>
        <publicationStatus>approvedSubtype</publicationStatus>
        <maintenanceAgency>
            <agencyName>American Numismatic Society</agencyName>
        </maintenanceAgency>
        <maintenanceStatus>derived</maintenanceStatus>
        <maintenanceHistory>
            <maintenanceEvent>
                <eventType>derived</eventType>
                <eventDateTime standardDateTime="2017-02-08T11:20:07-05:00">Wed, 08 Feb 2017 11:20:07 -0500</eventDateTime>
                <agentType>machine</agentType>
                <agent>PHP</agent>
                <eventDescription>Generated from OCRE CSV.</eventDescription>
            </maintenanceEvent>
        </maintenanceHistory>
        <rightsStmt>
            <copyrightHolder>American Numismatic Society</copyrightHolder>
            <license xlink:type="simple" xlink:href="http://opendatacommons.org/licenses/odbl/"/>
        </rightsStmt>
        <semanticDeclaration>
            <prefix>dcterms</prefix>
            <namespace>http://purl.org/dc/terms/</namespace>
        </semanticDeclaration>
        <semanticDeclaration>
            <prefix>skos</prefix>
            <namespace>http://www.w3.org/2004/02/skos/core#</namespace>
        </semanticDeclaration>
        <semanticDeclaration>
            <prefix>nmo</prefix>
            <namespace>http://nomisma.org/ontology#</namespace>
        </semanticDeclaration>
    </control>
    <descMeta>
        <title xml:lang="en">RIC IV Pescennius Niger 34B</title>
        <typeDesc>
            <dateRange>
                <fromDate standardDate="0193">AD 193</fromDate>
                <toDate standardDate="0194">AD 194</toDate>
            </dateRange>
            <objectType xlink:type="simple" xlink:href="http://nomisma.org/id/coin">Coin</objectType>
            <manufacture xlink:type="simple" xlink:href="http://nomisma.org/id/struck">Struck</manufacture>
            <denomination xlink:type="simple" xlink:href="http://nomisma.org/id/denarius">Denarius</denomination>
            <material xlink:type="simple" xlink:href="http://nomisma.org/id/ar">Silver</material>
            <authority>
                <persname xlink:type="simple" xlink:role="authority" xlink:href="http://nomisma.org/id/pescennius_niger">Pescennius Niger</persname>
            </authority>
            <geographic>
                <geogname xlink:type="simple" xlink:role="mint" xlink:href="http://nomisma.org/id/antiocheia_syria">Antioch</geogname>
                <geogname xlink:type="simple" xlink:role="region" xlink:href="http://nomisma.org/id/syria">Syria</geogname>
            </geographic>
            <obverse>
                <legend scriptCode="Latn">IMP CAES C PESC NIGER IVSTI AV</legend>
                <type>
                    <description xml:lang="en">Head of Pescennius Niger, laureate, right</description>
                </type>
                <persname xlink:type="simple" xlink:role="portrait" xlink:href="http://nomisma.org/id/pescennius_niger">Pescennius Niger</persname>
            </obverse>
            <reverse>
                <legend scriptCode="Latn">INVICTO IMPERAT</legend>
                <type>
                    <description xml:lang="en">Trophy and arms</description>
                </type>
            </reverse>
        </typeDesc>
    </descMeta>
</nuds>