<nuds xmlns="http://nomisma.org/nuds" xmlns:xsi="http://www.w3.org/2001/XMLSchema-instance" xmlns:xs="http://www.w3.org/2001/XMLSchema" xmlns:xlink="http://www.w3.org/1999/xlink" recordType="conceptual">
    <control>
        <recordId>ric.5.pro.623</recordId>
        <publicationStatus>approved</publicationStatus>
        <maintenanceAgency>
            <agencyName>American Numismatic Society</agencyName>
        </maintenanceAgency>
        <maintenanceStatus>derived</maintenanceStatus>
        <maintenanceHistory>
            <maintenanceEvent>
                <eventType>derived</eventType>
                <eventDateTime standardDateTime="2015-12-07T13:45:46-05:00">Mon, 07 Dec 2015 13:45:46 -0500</eventDateTime>
                <agentType>machine</agentType>
                <agent>PHP</agent>
                <eventDescription>Generated from OCRE CSV.</eventDescription>
            </maintenanceEvent>
        </maintenanceHistory>
        <rightsStmt>
            <copyrightHolder>American Numismatic Society</copyrightHolder>
            <license xlink:type="simple" xlink:href="http://opendatacommons.org/licenses/odbl/"/>
        </rightsStmt>
        <semanticDeclaration>
            <prefix>dcterms</prefix>
            <namespace>http://purl.org/dc/terms/</namespace>
        </semanticDeclaration>
        <semanticDeclaration>
            <prefix>skos</prefix>
            <namespace>http://www.w3.org/2004/02/skos/core#</namespace>
        </semanticDeclaration>
        <semanticDeclaration>
            <prefix>nmo</prefix>
            <namespace>http://nomisma.org/ontology#</namespace>
        </semanticDeclaration>
    </control>
    <descMeta>
        <title xml:lang="en">RIC V Probus 623</title>
        <typeDesc>
            <dateRange>
                <fromDate standardDate="0276">AD 276</fromDate>
                <toDate standardDate="0282">AD 282</toDate>
            </dateRange>
            <objectType xlink:type="simple" xlink:href="http://nomisma.org/id/coin">Coin</objectType>
            <manufacture xlink:type="simple" xlink:href="http://nomisma.org/id/struck">Struck</manufacture>
            <denomination xlink:type="simple" xlink:href="http://nomisma.org/id/antoninianus">Antoninianus</denomination>
            <material xlink:type="simple" xlink:href="http://nomisma.org/id/ar">Silver</material>
            <authority>
                <persname xlink:type="simple" xlink:role="authority" xlink:href="http://nomisma.org/id/probus">Probus</persname>
            </authority>
            <geographic>
                <geogname xlink:type="simple" xlink:role="mint" xlink:href="http://nomisma.org/id/siscia">Siscia</geogname>
                <geogname xlink:type="simple" xlink:role="region" xlink:href="http://nomisma.org/id/pannonia">Pannonia</geogname>
            </geographic>
            <obverse>
                <legend scriptCode="Latn">IMP PROBVS INV AVG</legend>
                <type>
                    <description xml:lang="en">Bust of Probus, radiate, draped, right</description>
                </type>
                <persname xlink:type="simple" xlink:role="portrait" xlink:href="http://nomisma.org/id/probus">Probus</persname>
            </obverse>
            <reverse>
                <legend scriptCode="Latn">ABVNDANTIA AVG N</legend>
                <type>
                    <description xml:lang="en">Abundantia, draped, standing right or left, emptying cornucopiae</description>
                </type>
                <persname xlink:type="simple" xlink:role="deity" xlink:href="http://collection.britishmuseum.org/id/person-institution/64218">Abundantia</persname>
                <symbol localType="mintMark">-/-//XXI</symbol>
            </reverse>
        </typeDesc>
    </descMeta>
</nuds>